odoo/addons/l10n_br_pos/README.rst
odoo/addons/l10n_br_pos/__init__.py
odoo/addons/l10n_br_pos/__manifest__.py
odoo/addons/l10n_br_pos/data/l10n_br_fiscal_cfop_data.xml
odoo/addons/l10n_br_pos/demo/pos_config_demo.xml
odoo/addons/l10n_br_pos/demo/pos_payment_method_demo.xml
odoo/addons/l10n_br_pos/demo/product_template_demo.xml
odoo/addons/l10n_br_pos/i18n/l10n_br_pos.pot
odoo/addons/l10n_br_pos/i18n/pt_BR.po
odoo/addons/l10n_br_pos/migration/14.0.1.1.0/pre-migration.py
odoo/addons/l10n_br_pos/models/__init__.py
odoo/addons/l10n_br_pos/models/cfop.py
odoo/addons/l10n_br_pos/models/document_related.py
odoo/addons/l10n_br_pos/models/l10n_br_pos_product_fiscal_map.py
odoo/addons/l10n_br_pos/models/mail_thread.py
odoo/addons/l10n_br_pos/models/pos_config.py
odoo/addons/l10n_br_pos/models/pos_order.py
odoo/addons/l10n_br_pos/models/pos_order_line.py
odoo/addons/l10n_br_pos/models/product_product.py
odoo/addons/l10n_br_pos/models/product_template.py
odoo/addons/l10n_br_pos/models/res_company.py
odoo/addons/l10n_br_pos/models/res_partner.py
odoo/addons/l10n_br_pos/models/stock.py
odoo/addons/l10n_br_pos/readme/CONFIGURE.rst
odoo/addons/l10n_br_pos/readme/CONTRIBUTORS.rst
odoo/addons/l10n_br_pos/readme/CREDITS.rst
odoo/addons/l10n_br_pos/readme/DESCRIPTION.rst
odoo/addons/l10n_br_pos/readme/HISTORY.rst
odoo/addons/l10n_br_pos/readme/INSTALL.rst
odoo/addons/l10n_br_pos/security/l10n_br_pos_product_fiscal_map.xml
odoo/addons/l10n_br_pos/static/description/icon.png
odoo/addons/l10n_br_pos/static/description/index.html
odoo/addons/l10n_br_pos/static/lib/JsBarcode.js
odoo/addons/l10n_br_pos/static/lib/qrcode.js
odoo/addons/l10n_br_pos/static/src/js/models.js
odoo/addons/l10n_br_pos/static/src/js/util.js
odoo/addons/l10n_br_pos/static/src/js/Screens/OrderManagementScreen/OrderRow.js
odoo/addons/l10n_br_pos/static/src/js/Screens/OrderManagementScreen/ControlButtons/CancelOrderButton.js
odoo/addons/l10n_br_pos/static/src/js/Screens/PaymentScreen/PaymentScreen.js
odoo14_addon_l10n_br_pos-14.0.1.5.4.dist-info/METADATA
odoo14_addon_l10n_br_pos-14.0.1.5.4.dist-info/WHEEL
odoo14_addon_l10n_br_pos-14.0.1.5.4.dist-info/top_level.txt
odoo14_addon_l10n_br_pos-14.0.1.5.4.dist-info/RECORD
