Metadata-Version: 2.1
Name: odoo14-addon-l10n_br_pos
Version: 14.0.1.5.4
Summary: Ponto de venda adaptado a legislação Brasileira
Home-page: https://github.com/OCA/l10n-brazil
Author: KMEE, Odoo Community Association (OCA)
Author-email: support@odoo-community.org
License: AGPL-3
Classifier: Programming Language :: Python
Classifier: Framework :: Odoo
Classifier: Framework :: Odoo :: 14.0
Classifier: License :: OSI Approved :: GNU Affero General Public License v3
Classifier: Development Status :: 3 - Alpha
Requires-Python: >=3.6
Requires-Dist: erpbrasil.base
Requires-Dist: odoo14-addon-l10n-br-account
Requires-Dist: odoo14-addon-l10n-br-base
Requires-Dist: odoo14-addon-l10n-br-fiscal
Requires-Dist: odoo14-addon-l10n-br-stock
Requires-Dist: odoo14-addon-l10n-br-zip
Requires-Dist: odoo<14.1dev,>=14.0a
